blyss-0.2.2.dist-info/METADATA
blyss-0.2.2.dist-info/WHEEL
blyss/api.py
blyss/bloom.py
blyss/blyss_lib.py
blyss/bucket.py
blyss/bucket_service.py
blyss/main.py
blyss/seed.py
blyss/serializer.py
blyss/varint.py
blyss/__init__.py
blyss/blyss.cp312-win_amd64.pyd
blyss-0.2.2.dist-info/RECORD
