Metadata-Version: 2.3
Name: blyss
Version: 0.2.2
Classifier: Programming Language :: Rust
Classifier: Programming Language :: Python :: Implementation :: CPython
Classifier: Programming Language :: Python :: Implementation :: PyPy
Requires-Dist: requests
Requires-Dist: httpx
Summary: An SDK for private data retrieval, built on homomorphic encryption.
Keywords: privacy,homomorphic,encryption,cryptography
Requires-Python: >=3.8
Project-URL: homepage, https://blyss.dev
Project-URL: documentation, https://docs.blyss.dev
Project-URL: repository, https://github.com/blyssprivacy/sdk
Project-URL: changelog, https://github.com/blyssprivacy/sdk/releases
